turtlecoin/__init__.py
turtlecoin/__version__.py
turtlecoin/daemon.py
turtlecoin/turtlecoind.py
turtlecoin/utils.py
turtlecoin/wallet.py
turtlecoin/walletd.py
turtlecoin-0.2.2.dist-info/DESCRIPTION.rst
turtlecoin-0.2.2.dist-info/METADATA
turtlecoin-0.2.2.dist-info/RECORD
turtlecoin-0.2.2.dist-info/WHEEL
turtlecoin-0.2.2.dist-info/metadata.json
turtlecoin-0.2.2.dist-info/top_level.txt
