Metadata-Version: 2.0
Name: turtlecoin
Version: 0.2.2
Summary: A Python wrapper for the TurtleCoin JSON-RPC interface
Home-page: https://github.com/arthurk/turtlecoin-python/
Author: Arthur Koziel
Author-email: arthur@arthurkoziel.com
License: MIT
Platform: UNKNOWN
Classifier: License :: OSI Approved :: MIT License
Classifier: Programming Language :: Python
Classifier: Programming Language :: Python :: 3
Classifier: Programming Language :: Python :: 3.6
Classifier: Programming Language :: Python :: Implementation :: CPython
Classifier: Programming Language :: Python :: Implementation :: PyPy
Requires-Python: >=3.6.0
Requires-Dist: requests
Provides-Extra: docs
Requires-Dist: sphinx (>=1.7); extra == 'docs'
Requires-Dist: sphinx-rtd-theme; extra == 'docs'
